zipfile_helper/__init__.py
zipfile_helper/base/base.py
zipfile_helper/extractor/extractor.py
zipfile_helper/metadata/metadata.py
zipfile_helper/reader/reader.py
zipfile_helper-0.1.2.dist-info/METADATA
zipfile_helper-0.1.2.dist-info/WHEEL
zipfile_helper-0.1.2.dist-info/licenses/LICENSE
zipfile_helper-0.1.2.dist-info/RECORD
