Metadata-Version: 2.4
Name: zipfile_helper
Version: 0.1.2
Summary: Reading and extracting zip files made easier
Project-URL: Documentation, https://github.com/Nyx-o/ZipfileHelper
Author-email: Nyx-0 <nyx.deusexmachina@proton.me>
License-Expression: MIT
License-File: LICENSE
Classifier: Operating System :: OS Independent
Classifier: Programming Language :: Python :: 3
Requires-Python: >=3.12.3
